mcp_server_sqlite_cn/__init__.py
mcp_server_sqlite_cn/server.py
mcp_server_sqlite_cn-2025.1.14.dist-info/METADATA
mcp_server_sqlite_cn-2025.1.14.dist-info/WHEEL
mcp_server_sqlite_cn-2025.1.14.dist-info/entry_points.txt
mcp_server_sqlite_cn-2025.1.14.dist-info/RECORD
