Metadata-Version: 2.4
Name: mcp-server-sqlite-cn
Version: 2025.1.14
Summary: A simple SQLite MCP server
Requires-Python: >=3.10.2
Requires-Dist: mcp>=1.0.0
